setup.cfg
setup.py
gaupro/BayesianOptimizer.py
gaupro/Regressor.py
gaupro/__init__.py
gaupro/acquisition_functions.py
gaupro/kernels.py
gaupro/policies.py
gaupro/utils.py
gaupro.egg-info/PKG-INFO
gaupro.egg-info/SOURCES.txt
gaupro.egg-info/dependency_links.txt
gaupro.egg-info/not-zip-safe
gaupro.egg-info/requires.txt
gaupro.egg-info/top_level.txt