Metadata-Version: 1.1
Name: gaupro
Version: 0.2.0
Summary: A Python implementation of the Gaussian Processes framework
Home-page: https://github.com/tsitsimis/gaupro
Author: Theodore Tsitsimis
Author-email: th.tsitsimis@gmail.com
License: MIT
Download-URL: https://github.com/tsitsimis/gaupro/archive/0.2.0.tar.gz
Keywords: gaussian-process,machine-learning
Platform: UNKNOWN
Classifier: Development Status :: 3 - Alpha
Classifier: Intended Audience :: Developers
Classifier: Topic :: Software Development :: Build Tools
Classifier: License :: OSI Approved :: MIT License
Classifier: Programming Language :: Python :: 3.4
